{
  "meta": {
    "title": "Nguyen Van Hung",
    "description": "Nguyen Van Hung Curriculum Vitae",
    "keywords": "cv, nguyen van hung, resume, linkedin"
  },
  "info": {
    "name": "Nguyen Van Hung",
    "location": "Ha Noi, VN",
    "mobile": "+84971015832",
    "email": "vanhung1999dev@gmail.com",
    "linkedin": "https://www.linkedin.com/in/hungnv1999"
  },
  "summary": [
    "I have more than 2 years of experience in the software industry with Nodejs and Reactjs",
    "familiar with Database (MongoDb, Mysql, Postgres)",
    "I have understand about OOP, SOLID principles, good algorithmic thinking as well as the ability to solve problem" 
  ],
  "skills": [
    {
      "title": "Language",
      "detail": "Java, Javascript, Nodejs, Html, Css."
    },
    {
      "title": "Database",
      "detail": "MongoDB, Postgres, Mysql."
    },
    {
      "title": "Cloud",
      "detail": "AWS."
    },
    {
      "title": "Virtual Machine",
      "detail": "Docker."
    },
    {
      "title": "Git",
      "detail": "Github, GitLab."
    },
    {
      "title": "OS",
      "detail": "Linux, MacOS."
    },
    {
      "title": "Soft Skill",
      "detail": "self-touch, proactive, team work."
    }
  ],
  "history": [
    {
      "title": "Software Developer",
      "company": "FPT Software",
      "time": "June 2021 to present",
      "skills": "Nodejs, ReactJs, Redux, Postgres, MongoDB, Redis, SocketIO, PHP, Docker, JestJs, Cron-job, SQS",
      "projects": [ 
        {
          "name": "Video Visit",
          "description": "Application helping organizations manage, Doctors can setup schedules, remind patients, can make a call to exchange in real-time.",
          "responsibilities": [
            "Join the daily meeting to discuss about the issue.",
            "Fix bug on both Front-End && Back-End.",
            "Provide solution to help system better."
          ]
        }
      ]
    },
    {
      "title": "Software Developer",
      "company": "TuyenSinh247",
      "time": "April 2020 to June 2021",
      "skills": "Nodejs, JWT, Sequelize, SES",
      "projects": [
        {
          "name": "App TS247",
          "description": "App TS247 help students learn online through smart phone and have best approach to improve the knowledge with high quality video lectures, which design to follow the knowledge of textbooks",
          "responsibilities": [
            "Implement all of assigned features.",
            "Refactor code.",
            "Write DOC for API.",
            "Fix bug."
          ]
        },
        {
          "name": "Backup Video",
          "description": "Helping the support reachers team can easily schedule recording, approve videos, filming team can upload product videos, check the status of uploaded videos.In addition, the system also backup files(video) to GCL",
          "responsibilities": [
            "Implement feature help cameraman find schedule, status of video both on Front-End && Back-End.",
            "Research new technical and implement it.",
            "Fix bug",
            "Write DOC"
          ]
        },
        {
          "name": "Tool CareSoft CallLog",
          "description": "Tool help developer can init data from system CareSoft and get data every hour.",
          "responsibilities": [
            "Calculate times repeat to get data from CareSoft system.",
            "Implement feature initial data and get data every hour.",
            "Write DOC"
          ]
        }
      ]
    }
  ],
  "educations": [
    {
      "school": "Ha Noi University",
      "major": "Software Engineering",
      "time": "July 2017 to June 2021",
      "achievements": [
        "GPA: 2.7"
      ]
    }
  ]
}
